{
  "coord": {
    "lon": 92.6752,
    "lat": 11.7007
  },
  "weather": [
    {
      "id": 721,
      "main": "Haze",
      "description": "haze",
      "icon": "50n"
    }
  ],
  "base": "stations",
  "main": {
    "temp": 28.51,
    "feels_like": 30.92,
    "temp_min": 28.51,
    "temp_max": 28.51,
    "pressure": 1012,
    "humidity": 65,
    "sea_level": 1012,
    "grnd_level": 1008
  },
  "visibility": 5000,
  "wind": {
    "speed": 1.54,
    "deg": 70
  },
  "clouds": {
    "all": 20
  },
  "dt": 1774883152,
  "sys": {
    "type": 1,
    "id": 9215,
    "country": "IN",
    "sunrise": 1774828040,
    "sunset": 1774872010
  },
  "timezone": 19800,
  "id": 1278647,
  "name": "Andaman and Nicobar Islands",
  "cod": 200,
  "_last_updated_utc": "2026-03-30T15:05:52.380Z"
}